speech_splitter/__init__.py
speech_splitter/splitter.py
speech_splitter-0.0.6.dist-info/LICENSE
speech_splitter-0.0.6.dist-info/METADATA
speech_splitter-0.0.6.dist-info/WHEEL
speech_splitter-0.0.6.dist-info/entry_points.txt
speech_splitter-0.0.6.dist-info/top_level.txt
speech_splitter-0.0.6.dist-info/RECORD
