Metadata-Version: 2.1
Name: speech-splitter
Version: 0.0.6
Summary: A command-line tool to split a speech audio into separate sentences for language learners.
Author-email: Anatolii Bubenkov <bubenkoff@gmail.com>
Project-URL: Repository, https://github.com/bubenkoff/speech-splitter.git
Project-URL: Issues, https://github.com/bubenkoff/speech-splitter/issues
Keywords: language,speech,splitter,sentence,tool
Classifier: Development Status :: 5 - Production/Stable
Classifier: Programming Language :: Python :: 3
Classifier: License :: OSI Approved :: MIT License
Classifier: Operating System :: OS Independent
Requires-Python: >=3.8
License-File: LICENSE
Requires-Dist: moviepy>=1.0.3
Requires-Dist: openai>=1.46.0
Requires-Dist: pydub>=0.25.1
Requires-Dist: nltk>=3.9.1
Requires-Dist: progress>=1.6
Provides-Extra: dev
Requires-Dist: black; extra == "dev"
Requires-Dist: flake8-pyproject; extra == "dev"
Requires-Dist: flake8; extra == "dev"
Requires-Dist: pytest; extra == "dev"
Requires-Dist: pytest-mock; extra == "dev"
Requires-Dist: pytest-cov; extra == "dev"
Requires-Dist: build; extra == "dev"
Requires-Dist: twine; extra == "dev"
